live/__init__.py
live/args.py
live/livelist.py
live/log.py
live/main.py
live/param.py
live/recorder.py
live/task.py
live/user.py
live/utils.py
bilibili_live_recorder-0.7.1.dist-info/METADATA
bilibili_live_recorder-0.7.1.dist-info/WHEEL
bilibili_live_recorder-0.7.1.dist-info/entry_points.txt
bilibili_live_recorder-0.7.1.dist-info/top_level.txt
bilibili_live_recorder-0.7.1.dist-info/RECORD
