Metadata-Version: 2.1
Name: bilibili-live-recorder
Version: 0.7.1
Summary: This is a script to record bilibili lives, coding with asyncio
Home-page: https://github.com/yuuzao/bilibili-live-recorder
Author: yuzao
License: MIT
Keywords: bilibili live
Platform: unix
Requires-Dist: requests
Requires-Dist: loguru
Requires-Dist: yarl
